{"status_code":200,"headers":{"Server": "nginx/1.10.3 (Ubuntu)", "Date": "Sat, 05 Jun 2021 13:49:15 GMT", "Content-Type": "application/json", "Content-Length": "2880", "Connection": "keep-alive", "Last-Modified": "Sat, 05 Jun 2021 13:49:15 GMT", "Expires": "Sat, 05 Jun 2021 14:20:05 GMT", "X-Backend-Host": "b_ybs_api3_b3_api_met_no_locationforecast", "Access-Control-Allow-Origin": "*", "Access-Control-Allow-Methods": "GET", "Access-Control-Allow-Headers": "Origin", "Content-Encoding": "gzip", "Vary": "Accept, Accept-Encoding", "X-Varnish": "546740743", "Age": "0", "Via": "1.1 varnish (Varnish/6.2)", "Accept-Ranges": "bytes"},"data":{"type":"Feature","geometry":{"type":"Point","coordinates":[-9.642,52.031,250]},"properties":{"meta":{"updated_at":"2021-06-05T13:01:06Z","units":{"air_pressure_at_sea_level":"hPa","air_temperature":"celsius","cloud_area_fraction":"%","precipitation_amount":"mm","relative_humidity":"%","wind_from_direction":"degrees","wind_speed":"m/s"}},"timeseries":[{"time":"2021-06-05T13:00:00Z","data":{"instant":{"details":{"air_pressure_at_sea_level":1023.4,"air_temperature":13.5,"cloud_area_fraction":100.0,"relative_humidity":72.2,"wind_from_direction":277.7,"wind_speed":2.8}},"next_12_hours":{"summary":{"symbol_code":"partlycloudy_day"}},"next_1_hours":{"summary":{"symbol_code":"lightrain"},"details":{"precipitation_amount":0.1}},"next_6_hours":{"summary":{"symbol_code":"partlycloudy_day"},"details":{"precipitation_amount":0.1}}}},{"time":"2021-06-05T14:00:00Z","data":{"instant":{"details":{"air_pressure_at_sea_level":1023.2,"air_temperature":14.3,"cloud_area_fraction":99.2,"relative_humidity":66.6,"wind_from_direction":302.3,"wind_speed":2.8}},"next_12_hours":{"summary":{"symbol_code":"partlycloudy_day"}},"next_1_hours":{"summary":{"symbol_code":"partlycloudy_day"},"details":{"precipitation_amount":0.0}},"next_6_hours":{"summary":{"symbol_code":"partlycloudy_day"},"details":{"precipitation_amount":0.0}}}},{"time":"2021-06-05T15:00:00Z","data":{"instant":{"details":{"air_pressure_at_sea_level":1023.3,"air_temperature":14.6,"cloud_area_fraction":80.5,"relative_humidity":62.5,"wind_from_direction":312.7,"wind_speed":2.5}},"next_12_hours":{"summary":{"symbol_code":"partlycloudy_day"}},"next_1_hours":{"summary":{"symbol_code":"partlycloudy_day"},"details":{"precipitation_amount":0.0}},"next_6_hours":{"summary":{"symbol_code":"partlycloudy_day"},"details":{"precipitation_amount":0.0}}}},{"time":"2021-06-05T16:00:00Z","data":{"instant":{"details":{"air_pressure_at_sea_level":1023.5,"air_temperature":14.8,"cloud_area_fraction":76.6,"relative_humidity":61.3,"wind_from_direction":302.9,"wind_speed":2.7}},"next_12_hours":{"summary":{"symbol_code":"partlycloudy_day"}},"next_1_hours":{"summary":{"symbol_code":"partlycloudy_day"},"details":{"precipitation_amount":0.0}},"next_6_hours":{"summary":{"symbol_code":"partlycloudy_day"},"details":{"precipitation_amount":0.0}}}},{"time":"2021-06-05T17:00:00Z","data":{"instant":{"details":{"air_pressure_at_sea_level":1023.7,"air_temperature":14.3,"cloud_area_fraction":67.2,"relative_humidity":68.0,"wind_from_direction":299.5,"wind_speed":3.4}},"next_12_hours":{"summary":{"symbol_code":"partlycloudy_day"}},"next_1_hours":{"summary":{"symbol_code":"partlycloudy_day"},"details":{"precipitation_amount":0.0}},"next_6_hours":{"summary":{"symbol_code":"partlycloudy_day"},"details":{"precipitation_amount":0.0}}}},{"time":"2021-06-05T18:00:00Z","data":{"instant":{"details":{"air_pressure_at_sea_level":1024.2,"air_temperature":13.4,"cloud_area_fraction":50.8,"relative_humidity":70.8,"wind_from_direction":294.2,"wind_speed":3.7}},"next_12_hours":{"summary":{"symbol_code":"partlycloudy_night"}},"next_1_hours":{"summary":{"symbol_code":"partlycloudy_day"},"details":{"precipitation_amount":0.0}},"next_6_hours":{"summary":{"symbol_code":"partlycloudy_night"},"details":{"precipitation_amount":0.0}}}},{"time":"2021-06-05T19:00:00Z","data":{"instant":{"details":{"air_pressure_at_sea_level":1024.6,"air_temperature":12.6,"cloud_area_fraction":53.9,"relative_humidity":74.6,"wind_from_direction":291.5,"wind_speed":3.3}},"next_12_hours":{"summary":{"symbol_code":"partlycloudy_night"}},"next_1_hours":{"summary":{"symbol_code":"partlycloudy_day"},"details":{"precipitation_amount":0.0}},"next_6_hours":{"summary":{"symbol_code":"partlycloudy_night"},"details":{"precipitation_amount":0.0}}}},{"time":"2021-06-05T20:00:00Z","data":{"instant":{"details":{"air_pressure_at_sea_level":1025.2,"air_temperature":11.6,"cloud_area_fraction":40.6,"relative_humidity":82.2,"wind_from_direction":299.9,"wind_speed":2.3}},"next_12_hours":{"summary":{"symbol_code":"partlycloudy_day"}},"next_1_hours":{"summary":{"symbol_code":"partlycloudy_day"},"details":{"precipitation_amount":0.0}},"next_6_hours":{"summary":{"symbol_code":"partlycloudy_night"},"details":{"precipitation_amount":0.0}}}},{"time":"2021-06-05T21:00:00Z","data":{"instant":{"details":{"air_pressure_at_sea_level":1026.0,"air_temperature":9.6,"cloud_area_fraction":39.8,"relative_humidity":93.7,"wind_from_direction":315.1,"wind_speed":1.5}},"next_12_hours":{"summary":{"symbol_code":"partlycloudy_day"}},"next_1_hours":{"summary":{"symbol_code":"partlycloudy_night"},"details":{"precipitation_amount":0.0}},"next_6_hours":{"summary":{"symbol_code":"partlycloudy_night"},"details":{"precipitation_amount":0.0}}}},{"time":"2021-06-05T22:00:00Z","data":{"instant":{"details":{"air_pressure_at_sea_level":1026.6,"air_temperature":9.4,"cloud_area_fraction":60.9,"relative_humidity":95.9,"wind_from_direction":322.4,"wind_speed":1.4}},"next_12_hours":{"summary":{"symbol_code":"partlycloudy_day"}},"next_1_hours":{"summary":{"symbol_code":"partlycloudy_night"},"details":{"precipitation_amount":0.0}},"next_6_hours":{"summary":{"symbol_code":"partlycloudy_night"},"details":{"precipitation_amount":0.0}}}},{"time":"2021-06-05T23:00:00Z","data":{"instant":{"details":{"air_pressure_at_sea_level":1026.7,"air_temperature":9.2,"cloud_area_fraction":63.3,"relative_humidity":96.4,"wind_from_direction":332.6,"wind_speed":1.1}},"next_12_hours":{"summary":{"symbol_code":"partlycloudy_day"}},"next_1_hours":{"summary":{"symbol_code":"partlycloudy_night"},"details":{"precipitation_amount":0.0}},"next_6_hours":{"summary":{"symbol_code":"partlycloudy_night"},"details":{"precipitation_amount":0.0}}}},{"time":"2021-06-06T00:00:00Z","data":{"instant":{"details":{"air_pressure_at_sea_level":1026.7,"air_temperature":8.0,"cloud_area_fraction":39.1,"relative_humidity":98.2,"wind_from_direction":331.5,"wind_speed":1.6}},"next_12_hours":{"summary":{"symbol_code":"partlycloudy_day"}},"next_1_hours":{"summary":{"symbol_code":"partlycloudy_night"},"details":{"precipitation_amount":0.0}},"next_6_hours":{"summary":{"symbol_code":"partlycloudy_night"},"details":{"precipitation_amount":0.0}}}},{"time":"2021-06-06T01:00:00Z","data":{"instant":{"details":{"air_pressure_at_sea_level":1026.8,"air_temperature":8.0,"cloud_area_fraction":43.7,"relative_humidity":97.7,"wind_from_direction":326.8,"wind_speed":1.5}},"next_12_hours":{"summary":{"symbol_code":"partlycloudy_day"}},"next_1_hours":{"summary":{"symbol_code":"partlycloudy_night"},"details":{"precipitation_amount":0.0}},"next_6_hours":{"summary":{"symbol_code":"partlycloudy_night"},"details":{"precipitation_amount":0.0}}}},{"time":"2021-06-06T02:00:00Z","data":{"instant":{"details":{"air_pressure_at_sea_level":1026.9,"air_temperature":7.1,"cloud_area_fraction":38.3,"relative_humidity":98.0,"wind_from_direction":335.5,"wind_speed":1.8}},"next_12_hours":{"summary":{"symbol_code":"partlycloudy_day"}},"next_1_hours":{"summary":{"symbol_code":"partlycloudy_night"},"details":{"precipitation_amount":0.0}},"next_6_hours":{"summary":{"symbol_code":"partlycloudy_day"},"details":{"precipitation_amount":0.0}}}},{"time":"2021-06-06T03:00:00Z","data":{"instant":{"details":{"air_pressure_at_sea_level":1027.0,"air_temperature":7.0,"cloud_area_fraction":39.8,"relative_humidity":98.5,"wind_from_direction":338.2,"wind_speed":1.9}},"next_12_hours":{"summary":{"symbol_code":"partlycloudy_day"}},"next_1_hours":{"summary":{"symbol_code":"partlycloudy_night"},"details":{"precipitation_amount":0.0}},"next_6_hours":{"summary":{"symbol_code":"partlycloudy_day"},"details":{"precipitation_amount":0.0}}}},{"time":"2021-06-06T04:00:00Z","data":{"instant":{"details":{"air_pressure_at_sea_level":1027.2,"air_temperature":7.3,"cloud_area_fraction":51.6,"relative_humidity":98.3,"wind_from_direction":329.6,"wind_speed":1.7}},"next_12_hours":{"summary":{"symbol_code":"partlycloudy_day"}},"next_1_hours":{"summary":{"symbol_code":"partlycloudy_day"},"details":{"precipitation_amount":0.0}},"next_6_hours":{"summary":{"symbol_code":"partlycloudy_day"},"details":{"precipitation_amount":0.0}}}},{"time":"2021-06-06T05:00:00Z","data":{"instant":{"details":{"air_pressure_at_sea_level":1027.3,"air_temperature":8.0,"cloud_area_fraction":54.7,"relative_humidity":98.2,"wind_from_direction":2.0,"wind_speed":1.3}},"next_12_hours":{"summary":{"symbol_code":"partlycloudy_day"}},"next_1_hours":{"summary":{"symbol_code":"partlycloudy_day"},"details":{"precipitation_amount":0.0}},"next_6_hours":{"summary":{"symbol_code":"partlycloudy_day"},"details":{"precipitation_amount":0.0}}}},{"time":"2021-06-06T06:00:00Z","data":{"instant":{"details":{"air_pressure_at_sea_level":1027.1,"air_temperature":8.7,"cloud_area_fraction":53.1,"relative_humidity":93.2,"wind_from_direction":44.8,"wind_speed":1.0}},"next_12_hours":{"summary":{"symbol_code":"partlycloudy_day"}},"next_1_hours":{"summary":{"symbol_code":"partlycloudy_day"},"details":{"precipitation_amount":0.0}},"next_6_hours":{"summary":{"symbol_code":"partlycloudy_day"},"details":{"precipitation_amount":0.0}}}},{"time":"2021-06-06T07:00:00Z","data":{"instant":{"details":{"air_pressure_at_sea_level":1027.1,"air_temperature":9.5,"cloud_area_fraction":57.8,"relative_humidity":79.1,"wind_from_direction":7.0,"wind_speed":1.3}},"next_12_hours":{"summary":{"symbol_code":"partlycloudy_day"}},"next_1_hours":{"summary":{"symbol_code":"partlycloudy_day"},"details":{"precipitation_amount":0.0}},"next_6_hours":{"summary":{"symbol_code":"cloudy"},"details":{"precipitation_amount":0.0}}}},{"time":"2021-06-06T08:00:00Z","data":{"instant":{"details":{"air_pressure_at_sea_level":1027.3,"air_temperature":10.2,"cloud_area_fraction":60.2,"relative_humidity":75.9,"wind_from_direction":335.2,"wind_speed":1.4}},"next_12_hours":{"summary":{"symbol_code":"cloudy"}},"next_1_hours":{"summary":{"symbol_code":"partlycloudy_day"},"details":{"precipitation_amount":0.0}},"next_6_hours":{"summary":{"symbol_code":"cloudy"},"details":{"precipitation_amount":0.0}}}},{"time":"2021-06-06T09:00:00Z","data":{"instant":{"details":{"air_pressure_at_sea_level":1026.9,"air_temperature":11.1,"cloud_area_fraction":67.2,"relative_humidity":71.7,"wind_from_direction":5.9,"wind_speed":0.9}},"next_12_hours":{"summary":{"symbol_code":"cloudy"}},"next_1_hours":{"summary":{"symbol_code":"cloudy"},"details":{"precipitation_amount":0.0}},"next_6_hours":{"summary":{"symbol_code":"cloudy"},"details":{"precipitation_amount":0.0}}}},{"time":"2021-06-06T10:00:00Z","data":{"instant":{"details":{"air_pressure_at_sea_level":1026.7,"air_temperature":12.3,"cloud_area_fraction":96.1,"relative_humidity":67.1,"wind_from_direction":66.9,"wind_speed":0.6}},"next_12_hours":{"summary":{"symbol_code":"cloudy"}},"next_1_hours":{"summary":{"symbol_code":"cloudy"},"details":{"precipitation_amount":0.0}},"next_6_hours":{"summary":{"symbol_code":"partlycloudy_day"},"details":{"precipitation_amount":0.0}}}},{"time":"2021-06-06T11:00:00Z","data":{"instant":{"details":{"air_pressure_at_sea_level":1026.5,"air_temperature":13.6,"cloud_area_fraction":100.0,"relative_humidity":61.6,"wind_from_direction":164.1,"wind_speed":0.8}},"next_12_hours":{"summary":{"symbol_code":"cloudy"}},"next_1_hours":{"summary":{"symbol_code":"cloudy"},"details":{"precipitation_amount":0.0}},"next_6_hours":{"summary":{"symbol_code":"partlycloudy_day"},"details":{"precipitation_amount":0.0}}}},{"time":"2021-06-06T12:00:00Z","data":{"instant":{"details":{"air_pressure_at_sea_level":1026.2,"air_temperature":14.6,"cloud_area_fraction":100.0,"relative_humidity":53.3,"wind_from_direction":176.3,"wind_speed":1.6}},"next_12_hours":{"summary":{"symbol_code":"cloudy"}},"next_1_hours":{"summary":{"symbol_code":"cloudy"},"details":{"precipitation_amount":0.0}},"next_6_hours":{"summary":{"symbol_code":"partlycloudy_day"},"details":{"precipitation_amount":0.0}}}},{"time":"2021-06-06T13:00:00Z","data":{"instant":{"details":{"air_pressure_at_sea_level":1025.7,"air_temperature":15.9,"cloud_area_fraction":99.2,"relative_humidity":48.3,"wind_from_direction":193.5,"wind_speed":1.9}},"next_12_hours":{"summary":{"symbol_code":"cloudy"}},"next_1_hours":{"summary":{"symbol_code":"cloudy"},"details":{"precipitation_amount":0.0}},"next_6_hours":{"summary":{"symbol_code":"partlycloudy_day"},"details":{"precipitation_amount":0.0}}}},{"time":"2021-06-06T14:00:00Z","data":{"instant":{"details":{"air_pressure_at_sea_level":1025.2,"air_temperature":16.1,"cloud_area_fraction":89.1,"relative_humidity":51.4,"wind_from_direction":216.5,"wind_speed":2.9}},"next_12_hours":{"summary":{"symbol_code":"cloudy"}},"next_1_hours":{"summary":{"symbol_code":"partlycloudy_day"},"details":{"precipitation_amount":0.0}},"next_6_hours":{"summary":{"symbol_code":"partlycloudy_day"},"details":{"precipitation_amount":0.0}}}},{"time":"2021-06-06T15:00:00Z","data":{"instant":{"details":{"air_pressure_at_sea_level":1025.1,"air_temperature":14.9,"cloud_area_fraction":50.8,"relative_humidity":58.4,"wind_from_direction":233.0,"wind_speed":3.6}},"next_12_hours":{"summary":{"symbol_code":"cloudy"}},"next_1_hours":{"summary":{"symbol_code":"partlycloudy_day"},"details":{"precipitation_amount":0.0}},"next_6_hours":{"summary":{"symbol_code":"partlycloudy_day"},"details":{"precipitation_amount":0.0}}}},{"time":"2021-06-06T16:00:00Z","data":{"instant":{"details":{"air_pressure_at_sea_level":1024.9,"air_temperature":14.5,"cloud_area_fraction":67.2,"relative_humidity":58.1,"wind_from_direction":226.3,"wind_speed":3.0}},"next_12_hours":{"summary":{"symbol_code":"cloudy"}},"next_1_hours":{"summary":{"symbol_code":"partlycloudy_day"},"details":{"precipitation_amount":0.0}},"next_6_hours":{"summary":{"symbol_code":"cloudy"},"details":{"precipitation_amount":0.0}}}},{"time":"2021-06-06T17:00:00Z","data":{"instant":{"details":{"air_pressure_at_sea_level":1024.7,"air_temperature":13.5,"cloud_area_fraction":79.7,"relative_humidity":60.8,"wind_from_direction":228.5,"wind_speed":3.2}},"next_12_hours":{"summary":{"symbol_code":"cloudy"}},"next_1_hours":{"summary":{"symbol_code":"partlycloudy_day"},"details":{"precipitation_amount":0.0}},"next_6_hours":{"summary":{"symbol_code":"cloudy"},"details":{"precipitation_amount":0.0}}}},{"time":"2021-06-06T18:00:00Z","data":{"instant":{"details":{"air_pressure_at_sea_level":1024.8,"air_temperature":12.3,"cloud_area_fraction":100.0,"relative_humidity":63.4,"wind_from_direction":231.5,"wind_speed":2.9}},"next_12_hours":{"summary":{"symbol_code":"cloudy"}},"next_1_hours":{"summary":{"symbol_code":"partlycloudy_day"},"details":{"precipitation_amount":0.0}},"next_6_hours":{"summary":{"symbol_code":"cloudy"},"details":{"precipitation_amount":0.0}}}},{"time":"2021-06-06T19:00:00Z","data":{"instant":{"details":{"air_pressure_at_sea_level":1024.5,"air_temperature":11.6,"cloud_area_fraction":100.0,"relative_humidity":65.8,"wind_from_direction":214.4,"wind_speed":1.9}},"next_12_hours":{"summary":{"symbol_code":"cloudy"}},"next_1_hours":{"summary":{"symbol_code":"partlycloudy_day"},"details":{"precipitation_amount":0.0}},"next_6_hours":{"summary":{"symbol_code":"cloudy"},"details":{"precipitation_amount":0.0}}}},{"time":"2021-06-06T20:00:00Z","data":{"instant":{"details":{"air_pressure_at_sea_level":1024.4,"air_temperature":10.6,"cloud_area_fraction":98.4,"relative_humidity":73.5,"wind_from_direction":193.3,"wind_speed":1.4}},"next_12_hours":{"summary":{"symbol_code":"cloudy"}},"next_1_hours":{"summary":{"symbol_code":"cloudy"},"details":{"precipitation_amount":0.0}},"next_6_hours":{"summary":{"symbol_code":"cloudy"},"details":{"precipitation_amount":0.0}}}},{"time":"2021-06-06T21:00:00Z","data":{"instant":{"details":{"air_pressure_at_sea_level":1024.6,"air_temperature":9.1,"cloud_area_fraction":99.2,"relative_humidity":80.7,"wind_from_direction":205.8,"wind_speed":1.5}},"next_12_hours":{"summary":{"symbol_code":"cloudy"}},"next_1_hours":{"summary":{"symbol_code":"cloudy"},"details":{"precipitation_amount":0.0}},"next_6_hours":{"summary":{"symbol_code":"cloudy"},"details":{"precipitation_amount":0.0}}}},{"time":"2021-06-06T22:00:00Z","data":{"instant":{"details":{"air_pressure_at_sea_level":1024.5,"air_temperature":8.3,"cloud_area_fraction":100.0,"relative_humidity":86.8,"wind_from_direction":196.5,"wind_speed":1.2}},"next_12_hours":{"summary":{"symbol_code":"cloudy"}},"next_1_hours":{"summary":{"symbol_code":"cloudy"},"details":{"precipitation_amount":0.0}},"next_6_hours":{"summary":{"symbol_code":"cloudy"},"details":{"precipitation_amount":0.0}}}},{"time":"2021-06-06T23:00:00Z","data":{"instant":{"details":{"air_pressure_at_sea_level":1024.1,"air_temperature":8.5,"cloud_area_fraction":100.0,"relative_humidity":86.9,"wind_from_direction":178.7,"wind_speed":1.3}},"next_12_hours":{"summary":{"symbol_code":"cloudy"}},"next_1_hours":{"summary":{"symbol_code":"cloudy"},"details":{"precipitation_amount":0.0}},"next_6_hours":{"summary":{"symbol_code":"cloudy"},"details":{"precipitation_amount":0.0}}}},{"time":"2021-06-07T00:00:00Z","data":{"instant":{"details":{"air_pressure_at_sea_level":1023.7,"air_temperature":8.4,"cloud_area_fraction":100.0,"relative_humidity":86.8,"wind_from_direction":172.2,"wind_speed":1.4}},"next_12_hours":{"summary":{"symbol_code":"cloudy"}},"next_1_hours":{"summary":{"symbol_code":"cloudy"},"details":{"precipitation_amount":0.0}},"next_6_hours":{"summary":{"symbol_code":"cloudy"},"details":{"precipitation_amount":0.0}}}},{"time":"2021-06-07T01:00:00Z","data":{"instant":{"details":{"air_pressure_at_sea_level":1023.1,"air_temperature":8.4,"cloud_area_fraction":100.0,"relative_humidity":85.2,"wind_from_direction":170.0,"wind_speed":1.7}},"next_12_hours":{"summary":{"symbol_code":"cloudy"}},"next_1_hours":{"summary":{"symbol_code":"cloudy"},"details":{"precipitation_amount":0.0}},"next_6_hours":{"summary":{"symbol_code":"cloudy"},"details":{"precipitation_amount":0.0}}}},{"time":"2021-06-07T02:00:00Z","data":{"instant":{"details":{"air_pressure_at_sea_level":1022.6,"air_temperature":8.5,"cloud_area_fraction":98.4,"relative_humidity":82.6,"wind_from_direction":180.9,"wind_speed":2.2}},"next_12_hours":{"summary":{"symbol_code":"cloudy"}},"next_1_hours":{"summary":{"symbol_code":"cloudy"},"details":{"precipitation_amount":0.0}},"next_6_hours":{"summary":{"symbol_code":"cloudy"},"details":{"precipitation_amount":0.0}}}},{"time":"2021-06-07T03:00:00Z","data":{"instant":{"details":{"air_pressure_at_sea_level":1022.1,"air_temperature":8.9,"cloud_area_fraction":90.6,"relative_humidity":79.7,"wind_from_direction":185.8,"wind_speed":2.6}},"next_12_hours":{"summary":{"symbol_code":"cloudy"}},"next_1_hours":{"summary":{"symbol_code":"cloudy"},"details":{"precipitation_amount":0.0}},"next_6_hours":{"summary":{"symbol_code":"cloudy"},"details":{"precipitation_amount":0.0}}}},{"time":"2021-06-07T04:00:00Z","data":{"instant":{"details":{"air_pressure_at_sea_level":1021.9,"air_temperature":9.0,"cloud_area_fraction":97.7,"relative_humidity":82.1,"wind_from_direction":192.1,"wind_speed":2.9}},"next_12_hours":{"summary":{"symbol_code":"lightrain"}},"next_1_hours":{"summary":{"symbol_code":"cloudy"},"details":{"precipitation_amount":0.0}},"next_6_hours":{"summary":{"symbol_code":"cloudy"},"details":{"precipitation_amount":0.0}}}},{"time":"2021-06-07T05:00:00Z","data":{"instant":{"details":{"air_pressure_at_sea_level":1021.7,"air_temperature":9.1,"cloud_area_fraction":92.2,"relative_humidity":84.2,"wind_from_direction":188.2,"wind_speed":3.0}},"next_12_hours":{"summary":{"symbol_code":"lightrain"}},"next_1_hours":{"summary":{"symbol_code":"partlycloudy_day"},"details":{"precipitation_amount":0.0}},"next_6_hours":{"summary":{"symbol_code":"cloudy"},"details":{"precipitation_amount":0.1}}}},{"time":"2021-06-07T06:00:00Z","data":{"instant":{"details":{"air_pressure_at_sea_level":1021.4,"air_temperature":9.8,"cloud_area_fraction":58.6,"relative_humidity":84.3,"wind_from_direction":184.3,"wind_speed":3.4}},"next_12_hours":{"summary":{"symbol_code":"lightrain"}},"next_1_hours":{"summary":{"symbol_code":"cloudy"},"details":{"precipitation_amount":0.0}},"next_6_hours":{"summary":{"symbol_code":"cloudy"},"details":{"precipitation_amount":0.2}}}},{"time":"2021-06-07T07:00:00Z","data":{"instant":{"details":{"air_pressure_at_sea_level":1021.4,"air_temperature":10.6,"cloud_area_fraction":98.4,"relative_humidity":82.8,"wind_from_direction":189.6,"wind_speed":4.5}},"next_12_hours":{"summary":{"symbol_code":"lightrain"}},"next_1_hours":{"summary":{"symbol_code":"cloudy"},"details":{"precipitation_amount":0.0}},"next_6_hours":{"summary":{"symbol_code":"cloudy"},"details":{"precipitation_amount":0.2}}}},{"time":"2021-06-07T08:00:00Z","data":{"instant":{"details":{"air_pressure_at_sea_level":1021.3,"air_temperature":11.3,"cloud_area_fraction":98.4,"relative_humidity":79.6,"wind_from_direction":191.5,"wind_speed":5.0}},"next_12_hours":{"summary":{"symbol_code":"lightrain"}},"next_1_hours":{"summary":{"symbol_code":"cloudy"},"details":{"precipitation_amount":0.0}},"next_6_hours":{"summary":{"symbol_code":"cloudy"},"details":{"precipitation_amount":0.2}}}},{"time":"2021-06-07T09:00:00Z","data":{"instant":{"details":{"air_pressure_at_sea_level":1021.1,"air_temperature":12.5,"cloud_area_fraction":89.8,"relative_humidity":72.2,"wind_from_direction":191.9,"wind_speed":5.2}},"next_12_hours":{"summary":{"symbol_code":"lightrain"}},"next_1_hours":{"summary":{"symbol_code":"cloudy"},"details":{"precipitation_amount":0.0}},"next_6_hours":{"summary":{"symbol_code":"cloudy"},"details":{"precipitation_amount":0.4}}}},{"time":"2021-06-07T10:00:00Z","data":{"instant":{"details":{"air_pressure_at_sea_level":1021.0,"air_temperature":13.4,"cloud_area_fraction":100.0,"relative_humidity":70.5,"wind_from_direction":193.1,"wind_speed":5.7}},"next_12_hours":{"summary":{"symbol_code":"lightrain"}},"next_1_hours":{"summary":{"symbol_code":"cloudy"},"details":{"precipitation_amount":0.1}},"next_6_hours":{"summary":{"symbol_code":"lightrain"},"details":{"precipitation_amount":0.8}}}},{"time":"2021-06-07T11:00:00Z","data":{"instant":{"details":{"air_pressure_at_sea_level":1021.0,"air_temperature":13.4,"cloud_area_fraction":100.0,"relative_humidity":74.1,"wind_from_direction":193.5,"wind_speed":6.0}},"next_12_hours":{"summary":{"symbol_code":"rain"}},"next_1_hours":{"summary":{"symbol_code":"lightrain"},"details":{"precipitation_amount":0.1}},"next_6_hours":{"summary":{"symbol_code":"rain"},"details":{"precipitation_amount":1.4}}}},{"time":"2021-06-07T12:00:00Z","data":{"instant":{"details":{"air_pressure_at_sea_level":1020.8,"air_temperature":14.1,"cloud_area_fraction":91.4,"relative_humidity":73.1,"wind_from_direction":197.1,"wind_speed":6.5}},"next_12_hours":{"summary":{"symbol_code":"rain"}},"next_1_hours":{"summary":{"symbol_code":"cloudy"},"details":{"precipitation_amount":0.0}},"next_6_hours":{"summary":{"symbol_code":"rain"},"details":{"precipitation_amount":2.0}}}},{"time":"2021-06-07T13:00:00Z","data":{"instant":{"details":{"air_pressure_at_sea_level":1020.5,"air_temperature":14.4,"cloud_area_fraction":89.1,"relative_humidity":70.7,"wind_from_direction":195.5,"wind_speed":6.6}},"next_12_hours":{"summary":{"symbol_code":"rain"}},"next_1_hours":{"summary":{"symbol_code":"partlycloudy_day"},"details":{"precipitation_amount":0.0}},"next_6_hours":{"summary":{"symbol_code":"rain"},"details":{"precipitation_amount":2.6}}}},{"time":"2021-06-07T14:00:00Z","data":{"instant":{"details":{"air_pressure_at_sea_level":1020.2,"air_temperature":14.3,"cloud_area_fraction":75.0,"relative_humidity":71.9,"wind_from_direction":194.2,"wind_speed":6.8}},"next_12_hours":{"summary":{"symbol_code":"lightrain"}},"next_1_hours":{"summary":{"symbol_code":"lightrain"},"details":{"precipitation_amount":0.1}},"next_6_hours":{"summary":{"symbol_code":"rain"},"details":{"precipitation_amount":3.0}}}},{"time":"2021-06-07T15:00:00Z","data":{"instant":{"details":{"air_pressure_at_sea_level":1019.9,"air_temperature":14.2,"cloud_area_fraction":100.0,"relative_humidity":73.1,"wind_from_direction":189.8,"wind_speed":7.0}},"next_12_hours":{"summary":{"symbol_code":"lightrain"}},"next_1_hours":{"summary":{"symbol_code":"rain"},"details":{"precipitation_amount":0.5}},"next_6_hours":{"summary":{"symbol_code":"rain"},"details":{"precipitation_amount":3.2}}}},{"time":"2021-06-07T16:00:00Z","data":{"instant":{"details":{"air_pressure_at_sea_level":1019.7,"air_temperature":13.1,"cloud_area_fraction":100.0,"relative_humidity":83.7,"wind_from_direction":183.6,"wind_speed":6.3}},"next_12_hours":{"summary":{"symbol_code":"lightrain"}},"next_1_hours":{"summary":{"symbol_code":"rain"},"details":{"precipitation_amount":0.7}},"next_6_hours":{"summary":{"symbol_code":"rain"},"details":{"precipitation_amount":2.9}}}},{"time":"2021-06-07T17:00:00Z","data":{"instant":{"details":{"air_pressure_at_sea_level":1019.5,"air_temperature":12.8,"cloud_area_fraction":100.0,"relative_humidity":89.0,"wind_from_direction":180.4,"wind_speed":6.1}},"next_12_hours":{"summary":{"symbol_code":"lightrain"}},"next_1_hours":{"summary":{"symbol_code":"rain"},"details":{"precipitation_amount":0.7}},"next_6_hours":{"summary":{"symbol_code":"rain"},"details":{"precipitation_amount":2.2}}}},{"time":"2021-06-07T18:00:00Z","data":{"instant":{"details":{"air_pressure_at_sea_level":1019.3,"air_temperature":12.5,"cloud_area_fraction":100.0,"relative_humidity":93.5,"wind_from_direction":185.4,"wind_speed":5.5}},"next_12_hours":{"summary":{"symbol_code":"lightrain"}},"next_1_hours":{"summary":{"symbol_code":"rain"},"details":{"precipitation_amount":0.6}},"next_6_hours":{"summary":{"symbol_code":"rain"},"details":{"precipitation_amount":1.5}}}},{"time":"2021-06-07T19:00:00Z","data":{"instant":{"details":{"air_pressure_at_sea_level":1019.3,"air_temperature":12.2,"cloud_area_fraction":100.0,"relative_humidity":95.6,"wind_from_direction":187.6,"wind_speed":4.9}},"next_1_hours":{"summary":{"symbol_code":"rain"},"details":{"precipitation_amount":0.4}},"next_6_hours":{"summary":{"symbol_code":"rain"},"details":{"precipitation_amount":1.0}}}},{"time":"2021-06-07T20:00:00Z","data":{"instant":{"details":{"air_pressure_at_sea_level":1019.2,"air_temperature":12.1,"cloud_area_fraction":100.0,"relative_humidity":96.5,"wind_from_direction":189.6,"wind_speed":4.5}},"next_1_hours":{"summary":{"symbol_code":"rain"},"details":{"precipitation_amount":0.3}},"next_6_hours":{"summary":{"symbol_code":"lightrain"},"details":{"precipitation_amount":0.6}}}},{"time":"2021-06-07T21:00:00Z","data":{"instant":{"details":{"air_pressure_at_sea_level":1019.4,"air_temperature":12.2,"cloud_area_fraction":100.0,"relative_humidity":96.7,"wind_from_direction":190.3,"wind_speed":3.9}},"next_1_hours":{"summary":{"symbol_code":"lightrain"},"details":{"precipitation_amount":0.2}},"next_6_hours":{"summary":{"symbol_code":"cloudy"},"details":{"precipitation_amount":0.4}}}},{"time":"2021-06-07T22:00:00Z","data":{"instant":{"details":{"air_pressure_at_sea_level":1019.7,"air_temperature":12.2,"cloud_area_fraction":99.2,"relative_humidity":97.3,"wind_from_direction":198.3,"wind_speed":3.8}},"next_1_hours":{"summary":{"symbol_code":"cloudy"},"details":{"precipitation_amount":0.0}},"next_6_hours":{"summary":{"symbol_code":"cloudy"},"details":{"precipitation_amount":0.2}}}},{"time":"2021-06-07T23:00:00Z","data":{"instant":{"details":{"air_pressure_at_sea_level":1019.8,"air_temperature":12.1,"cloud_area_fraction":99.2,"relative_humidity":98.3,"wind_from_direction":197.2,"wind_speed":3.4}},"next_1_hours":{"summary":{"symbol_code":"cloudy"},"details":{"precipitation_amount":0.0}},"next_6_hours":{"summary":{"symbol_code":"cloudy"},"details":{"precipitation_amount":0.3}}}},{"time":"2021-06-08T00:00:00Z","data":{"instant":{"details":{"air_pressure_at_sea_level":1019.6,"air_temperature":12.1,"cloud_area_fraction":100.0,"relative_humidity":98.7,"wind_from_direction":187.6,"wind_speed":3.1}},"next_12_hours":{"summary":{"symbol_code":"lightrain"}},"next_1_hours":{"summary":{"symbol_code":"cloudy"},"details":{"precipitation_amount":0.1}},"next_6_hours":{"summary":{"symbol_code":"cloudy"},"details":{"precipitation_amount":0.3}}}},{"time":"2021-06-08T01:00:00Z","data":{"instant":{"details":{"air_pressure_at_sea_level":1019.3,"air_temperature":12.1,"cloud_area_fraction":100.0,"relative_humidity":98.7,"wind_from_direction":187.7,"wind_speed":3.3}},"next_1_hours":{"summary":{"symbol_code":"cloudy"},"details":{"precipitation_amount":0.0}}}},{"time":"2021-06-08T02:00:00Z","data":{"instant":{"details":{"air_pressure_at_sea_level":1019.1,"air_temperature":12.1,"cloud_area_fraction":100.0,"relative_humidity":98.5,"wind_from_direction":189.1,"wind_speed":3.4}},"next_1_hours":{"summary":{"symbol_code":"cloudy"},"details":{"precipitation_amount":0.0}}}},{"time":"2021-06-08T03:00:00Z","data":{"instant":{"details":{"air_pressure_at_sea_level":1018.8,"air_temperature":12.1,"cloud_area_fraction":100.0,"relative_humidity":99.0,"wind_from_direction":186.9,"wind_speed":3.4}},"next_1_hours":{"summary":{"symbol_code":"cloudy"},"details":{"precipitation_amount":0.0}}}},{"time":"2021-06-08T04:00:00Z","data":{"instant":{"details":{"air_pressure_at_sea_level":1018.7,"air_temperature":12.1,"cloud_area_fraction":100.0,"relative_humidity":99.2,"wind_from_direction":192.5,"wind_speed":3.6}},"next_1_hours":{"summary":{"symbol_code":"fog"},"details":{"precipitation_amount":0.0}}}},{"time":"2021-06-08T05:00:00Z","data":{"instant":{"details":{"air_pressure_at_sea_level":1018.8,"air_temperature":12.1,"cloud_area_fraction":100.0,"relative_humidity":99.2,"wind_from_direction":190.2,"wind_speed":3.8}},"next_1_hours":{"summary":{"symbol_code":"cloudy"},"details":{"precipitation_amount":0.1}}}},{"time":"2021-06-08T06:00:00Z","data":{"instant":{"details":{"air_pressure_at_sea_level":1018.9,"air_temperature":12.3,"cloud_area_fraction":100.0,"relative_humidity":98.6,"wind_from_direction":188.6,"wind_speed":4.1}},"next_12_hours":{"summary":{"symbol_code":"rain"}},"next_6_hours":{"summary":{"symbol_code":"rain"},"details":{"precipitation_amount":1.4}}}},{"time":"2021-06-08T12:00:00Z","data":{"instant":{"details":{"air_pressure_at_sea_level":1019.7,"air_temperature":14.1,"cloud_area_fraction":100.0,"relative_humidity":90.9,"wind_from_direction":175.9,"wind_speed":6.1}},"next_12_hours":{"summary":{"symbol_code":"rain"}},"next_6_hours":{"summary":{"symbol_code":"rain"},"details":{"precipitation_amount":1.8}}}},{"time":"2021-06-08T18:00:00Z","data":{"instant":{"details":{"air_pressure_at_sea_level":1017.8,"air_temperature":13.9,"cloud_area_fraction":100.0,"relative_humidity":95.0,"wind_from_direction":188.5,"wind_speed":4.6}},"next_12_hours":{"summary":{"symbol_code":"lightrain"}},"next_6_hours":{"summary":{"symbol_code":"rain"},"details":{"precipitation_amount":1.2}}}},{"time":"2021-06-09T00:00:00Z","data":{"instant":{"details":{"air_pressure_at_sea_level":1017.4,"air_temperature":13.0,"cloud_area_fraction":100.0,"relative_humidity":96.5,"wind_from_direction":191.0,"wind_speed":4.1}},"next_12_hours":{"summary":{"symbol_code":"lightrain"}},"next_6_hours":{"summary":{"symbol_code":"lightrain"},"details":{"precipitation_amount":0.8}}}},{"time":"2021-06-09T06:00:00Z","data":{"instant":{"details":{"air_pressure_at_sea_level":1017.5,"air_temperature":12.9,"cloud_area_fraction":100.0,"relative_humidity":97.6,"wind_from_direction":201.0,"wind_speed":3.3}},"next_12_hours":{"summary":{"symbol_code":"cloudy"}},"next_6_hours":{"summary":{"symbol_code":"cloudy"},"details":{"precipitation_amount":0.2}}}},{"time":"2021-06-09T12:00:00Z","data":{"instant":{"details":{"air_pressure_at_sea_level":1019.2,"air_temperature":15.5,"cloud_area_fraction":100.0,"relative_humidity":83.6,"wind_from_direction":214.2,"wind_speed":4.5}},"next_12_hours":{"summary":{"symbol_code":"lightrain"}},"next_6_hours":{"summary":{"symbol_code":"cloudy"},"details":{"precipitation_amount":0.1}}}},{"time":"2021-06-09T18:00:00Z","data":{"instant":{"details":{"air_pressure_at_sea_level":1018.7,"air_temperature":15.2,"cloud_area_fraction":100.0,"relative_humidity":88.8,"wind_from_direction":198.8,"wind_speed":4.4}},"next_12_hours":{"summary":{"symbol_code":"lightrain"}},"next_6_hours":{"summary":{"symbol_code":"lightrain"},"details":{"precipitation_amount":0.9}}}},{"time":"2021-06-10T00:00:00Z","data":{"instant":{"details":{"air_pressure_at_sea_level":1017.4,"air_temperature":13.5,"cloud_area_fraction":100.0,"relative_humidity":95.6,"wind_from_direction":188.2,"wind_speed":4.1}},"next_12_hours":{"summary":{"symbol_code":"lightrain"}},"next_6_hours":{"summary":{"symbol_code":"rain"},"details":{"precipitation_amount":1.2}}}},{"time":"2021-06-10T06:00:00Z","data":{"instant":{"details":{"air_pressure_at_sea_level":1015.6,"air_temperature":13.4,"cloud_area_fraction":100.0,"relative_humidity":97.5,"wind_from_direction":195.5,"wind_speed":4.6}},"next_12_hours":{"summary":{"symbol_code":"lightrain"}},"next_6_hours":{"summary":{"symbol_code":"lightrain"},"details":{"precipitation_amount":0.8}}}},{"time":"2021-06-10T12:00:00Z","data":{"instant":{"details":{"air_pressure_at_sea_level":1015.4,"air_temperature":15.0,"cloud_area_fraction":100.0,"relative_humidity":88.1,"wind_from_direction":198.0,"wind_speed":6.5}},"next_12_hours":{"summary":{"symbol_code":"rain"}},"next_6_hours":{"summary":{"symbol_code":"rain"},"details":{"precipitation_amount":3.7}}}},{"time":"2021-06-10T18:00:00Z","data":{"instant":{"details":{"air_pressure_at_sea_level":1013.4,"air_temperature":14.2,"cloud_area_fraction":100.0,"relative_humidity":96.7,"wind_from_direction":191.9,"wind_speed":3.9}},"next_12_hours":{"summary":{"symbol_code":"lightrainshowers_day"}},"next_6_hours":{"summary":{"symbol_code":"rain"},"details":{"precipitation_amount":1.8}}}},{"time":"2021-06-11T00:00:00Z","data":{"instant":{"details":{"air_pressure_at_sea_level":1013.6,"air_temperature":12.9,"cloud_area_fraction":100.0,"relative_humidity":96.6,"wind_from_direction":223.3,"wind_speed":2.7}},"next_12_hours":{"summary":{"symbol_code":"partlycloudy_day"}},"next_6_hours":{"summary":{"symbol_code":"partlycloudy_night"},"details":{"precipitation_amount":0.4}}}},{"time":"2021-06-11T06:00:00Z","data":{"instant":{"details":{"air_pressure_at_sea_level":1017.0,"air_temperature":10.1,"cloud_area_fraction":45.3,"relative_humidity":88.2,"wind_from_direction":312.3,"wind_speed":2.6}},"next_12_hours":{"summary":{"symbol_code":"cloudy"}},"next_6_hours":{"summary":{"symbol_code":"partlycloudy_day"},"details":{"precipitation_amount":0.0}}}},{"time":"2021-06-11T12:00:00Z","data":{"instant":{"details":{"air_pressure_at_sea_level":1020.3,"air_temperature":13.7,"cloud_area_fraction":97.7,"relative_humidity":63.9,"wind_from_direction":308.1,"wind_speed":4.4}},"next_12_hours":{"summary":{"symbol_code":"partlycloudy_day"}},"next_6_hours":{"summary":{"symbol_code":"cloudy"},"details":{"precipitation_amount":0.0}}}},{"time":"2021-06-11T18:00:00Z","data":{"instant":{"details":{"air_pressure_at_sea_level":1023.1,"air_temperature":12.3,"cloud_area_fraction":82.0,"relative_humidity":68.0,"wind_from_direction":322.0,"wind_speed":4.0}},"next_12_hours":{"summary":{"symbol_code":"fair_night"}},"next_6_hours":{"summary":{"symbol_code":"partlycloudy_night"},"details":{"precipitation_amount":0.0}}}},{"time":"2021-06-12T00:00:00Z","data":{"instant":{"details":{"air_pressure_at_sea_level":1026.5,"air_temperature":8.5,"cloud_area_fraction":17.2,"relative_humidity":89.9,"wind_from_direction":303.7,"wind_speed":1.6}},"next_12_hours":{"summary":{"symbol_code":"fair_day"}},"next_6_hours":{"summary":{"symbol_code":"fair_night"},"details":{"precipitation_amount":0.0}}}},{"time":"2021-06-12T06:00:00Z","data":{"instant":{"details":{"air_pressure_at_sea_level":1028.4,"air_temperature":9.2,"cloud_area_fraction":18.0,"relative_humidity":95.4,"wind_from_direction":226.7,"wind_speed":0.9}},"next_12_hours":{"summary":{"symbol_code":"fair_day"}},"next_6_hours":{"summary":{"symbol_code":"fair_day"},"details":{"precipitation_amount":0.0}}}},{"time":"2021-06-12T12:00:00Z","data":{"instant":{"details":{"air_pressure_at_sea_level":1029.7,"air_temperature":15.7,"cloud_area_fraction":52.3,"relative_humidity":66.3,"wind_from_direction":303.6,"wind_speed":0.9}},"next_12_hours":{"summary":{"symbol_code":"clearsky_day"}},"next_6_hours":{"summary":{"symbol_code":"fair_day"},"details":{"precipitation_amount":0.0}}}},{"time":"2021-06-12T18:00:00Z","data":{"instant":{"details":{"air_pressure_at_sea_level":1029.9,"air_temperature":16.0,"cloud_area_fraction":2.3,"relative_humidity":68.0,"wind_from_direction":313.1,"wind_speed":2.8}},"next_12_hours":{"summary":{"symbol_code":"fair_night"}},"next_6_hours":{"summary":{"symbol_code":"clearsky_night"},"details":{"precipitation_amount":0.0}}}},{"time":"2021-06-13T00:00:00Z","data":{"instant":{"details":{"air_pressure_at_sea_level":1031.8,"air_temperature":10.3,"cloud_area_fraction":0.8,"relative_humidity":93.1,"wind_from_direction":316.0,"wind_speed":0.8}},"next_12_hours":{"summary":{"symbol_code":"fair_day"}},"next_6_hours":{"summary":{"symbol_code":"fair_night"},"details":{"precipitation_amount":0.0}}}},{"time":"2021-06-13T06:00:00Z","data":{"instant":{"details":{"air_pressure_at_sea_level":1031.8,"air_temperature":9.9,"cloud_area_fraction":58.6,"relative_humidity":97.6,"wind_from_direction":194.2,"wind_speed":0.3}},"next_12_hours":{"summary":{"symbol_code":"clearsky_day"}},"next_6_hours":{"summary":{"symbol_code":"fair_day"},"details":{"precipitation_amount":0.0}}}},{"time":"2021-06-13T12:00:00Z","data":{"instant":{"details":{"air_pressure_at_sea_level":1032.2,"air_temperature":19.0,"cloud_area_fraction":0.0,"relative_humidity":55.5,"wind_from_direction":268.3,"wind_speed":0.7}},"next_12_hours":{"summary":{"symbol_code":"partlycloudy_day"}},"next_6_hours":{"summary":{"symbol_code":"clearsky_day"},"details":{"precipitation_amount":0.0}}}},{"time":"2021-06-13T18:00:00Z","data":{"instant":{"details":{"air_pressure_at_sea_level":1030.6,"air_temperature":18.6,"cloud_area_fraction":0.8,"relative_humidity":71.5,"wind_from_direction":318.4,"wind_speed":2.7}},"next_12_hours":{"summary":{"symbol_code":"cloudy"}},"next_6_hours":{"summary":{"symbol_code":"partlycloudy_night"},"details":{"precipitation_amount":0.0}}}},{"time":"2021-06-14T00:00:00Z","data":{"instant":{"details":{"air_pressure_at_sea_level":1031.0,"air_temperature":9.9,"cloud_area_fraction":86.7,"relative_humidity":100.0,"wind_from_direction":25.8,"wind_speed":1.6}},"next_12_hours":{"summary":{"symbol_code":"partlycloudy_day"}},"next_6_hours":{"summary":{"symbol_code":"cloudy"},"details":{"precipitation_amount":0.0}}}},{"time":"2021-06-14T06:00:00Z","data":{"instant":{"details":{"air_pressure_at_sea_level":1028.4,"air_temperature":11.2,"cloud_area_fraction":100.0,"relative_humidity":98.2,"wind_from_direction":115.8,"wind_speed":0.6}},"next_12_hours":{"summary":{"symbol_code":"fair_day"}},"next_6_hours":{"summary":{"symbol_code":"partlycloudy_day"},"details":{"precipitation_amount":0.0}}}},{"time":"2021-06-14T12:00:00Z","data":{"instant":{"details":{"air_pressure_at_sea_level":1026.9,"air_temperature":21.8,"cloud_area_fraction":16.4,"relative_humidity":63.5,"wind_from_direction":189.7,"wind_speed":1.4}},"next_6_hours":{"summary":{"symbol_code":"fair_day"},"details":{"precipitation_amount":0.0}}}},{"time":"2021-06-14T18:00:00Z","data":{"instant":{"details":{"air_pressure_at_sea_level":1024.2,"air_temperature":19.5,"cloud_area_fraction":15.6,"relative_humidity":74.8,"wind_from_direction":335.6,"wind_speed":2.1}}}}]}}
}