{"status_code":200,"headers":{"Server": "nginx/1.10.3 (Ubuntu)", "Date": "Thu, 23 Sep 2021 20:26:22 GMT", "Content-Type": "application/json", "Content-Length": "2659", "Connection": "keep-alive", "Expires": "Thu, 23 Sep 2021 20:58:16 GMT", "Last-Modified": "Thu, 23 Sep 2021 20:26:22 GMT", "X-Backend-Host": "b_ybs_api3_b3_api_met_no_locationforecast", "Access-Control-Allow-Origin": "*", "Access-Control-Allow-Methods": "GET", "Access-Control-Allow-Headers": "Origin", "Content-Encoding": "gzip", "Vary": "Accept, Accept-Encoding", "X-Varnish": "1018142281", "Age": "0", "Via": "1.1 varnish (Varnish/6.2)", "Accept-Ranges": "bytes"},"data":{"type":"Feature","geometry":{"type":"Point","coordinates":[-9.357,53.071,25]},"properties":{"meta":{"updated_at":"2021-09-23T13:19:49Z","units":{"air_pressure_at_sea_level":"hPa","air_temperature":"celsius","cloud_area_fraction":"%","precipitation_amount":"mm","relative_humidity":"%","wind_from_direction":"degrees","wind_speed":"m/s"}},"timeseries":[{"time":"2021-09-23T20:00:00Z","data":{"instant":{"details":{"air_pressure_at_sea_level":1019.9,"air_temperature":14.7,"cloud_area_fraction":100.0,"relative_humidity":89.8,"wind_from_direction":238.7,"wind_speed":4.4}},"next_12_hours":{"summary":{"symbol_code":"rain"}},"next_1_hours":{"summary":{"symbol_code":"cloudy"},"details":{"precipitation_amount":0.0}},"next_6_hours":{"summary":{"symbol_code":"rain"},"details":{"precipitation_amount":1.3}}}},{"time":"2021-09-23T21:00:00Z","data":{"instant":{"details":{"air_pressure_at_sea_level":1019.4,"air_temperature":15.2,"cloud_area_fraction":100.0,"relative_humidity":92.5,"wind_from_direction":225.6,"wind_speed":4.9}},"next_12_hours":{"summary":{"symbol_code":"rain"}},"next_1_hours":{"summary":{"symbol_code":"cloudy"},"details":{"precipitation_amount":0.1}},"next_6_hours":{"summary":{"symbol_code":"rain"},"details":{"precipitation_amount":1.5}}}},{"time":"2021-09-23T22:00:00Z","data":{"instant":{"details":{"air_pressure_at_sea_level":1018.9,"air_temperature":15.5,"cloud_area_fraction":100.0,"relative_humidity":95.2,"wind_from_direction":227.8,"wind_speed":6.4}},"next_12_hours":{"summary":{"symbol_code":"rain"}},"next_1_hours":{"summary":{"symbol_code":"rain"},"details":{"precipitation_amount":0.3}},"next_6_hours":{"summary":{"symbol_code":"rain"},"details":{"precipitation_amount":1.7}}}},{"time":"2021-09-23T23:00:00Z","data":{"instant":{"details":{"air_pressure_at_sea_level":1018.4,"air_temperature":15.8,"cloud_area_fraction":100.0,"relative_humidity":97.1,"wind_from_direction":228.3,"wind_speed":6.1}},"next_12_hours":{"summary":{"symbol_code":"rain"}},"next_1_hours":{"summary":{"symbol_code":"rain"},"details":{"precipitation_amount":0.4}},"next_6_hours":{"summary":{"symbol_code":"rain"},"details":{"precipitation_amount":1.5}}}},{"time":"2021-09-24T00:00:00Z","data":{"instant":{"details":{"air_pressure_at_sea_level":1017.8,"air_temperature":15.9,"cloud_area_fraction":100.0,"relative_humidity":97.6,"wind_from_direction":234.5,"wind_speed":6.0}},"next_12_hours":{"summary":{"symbol_code":"rain"}},"next_1_hours":{"summary":{"symbol_code":"rain"},"details":{"precipitation_amount":0.3}},"next_6_hours":{"summary":{"symbol_code":"rain"},"details":{"precipitation_amount":1.2}}}},{"time":"2021-09-24T01:00:00Z","data":{"instant":{"details":{"air_pressure_at_sea_level":1017.2,"air_temperature":15.9,"cloud_area_fraction":100.0,"relative_humidity":97.6,"wind_from_direction":240.1,"wind_speed":6.2}},"next_12_hours":{"summary":{"symbol_code":"rain"}},"next_1_hours":{"summary":{"symbol_code":"lightrain"},"details":{"precipitation_amount":0.2}},"next_6_hours":{"summary":{"symbol_code":"rain"},"details":{"precipitation_amount":1.5}}}},{"time":"2021-09-24T02:00:00Z","data":{"instant":{"details":{"air_pressure_at_sea_level":1016.9,"air_temperature":15.9,"cloud_area_fraction":100.0,"relative_humidity":97.8,"wind_from_direction":250.0,"wind_speed":6.5}},"next_12_hours":{"summary":{"symbol_code":"rain"}},"next_1_hours":{"summary":{"symbol_code":"rain"},"details":{"precipitation_amount":0.3}},"next_6_hours":{"summary":{"symbol_code":"rain"},"details":{"precipitation_amount":2.5}}}},{"time":"2021-09-24T03:00:00Z","data":{"instant":{"details":{"air_pressure_at_sea_level":1016.7,"air_temperature":15.8,"cloud_area_fraction":100.0,"relative_humidity":97.6,"wind_from_direction":250.1,"wind_speed":6.4}},"next_12_hours":{"summary":{"symbol_code":"rain"}},"next_1_hours":{"summary":{"symbol_code":"lightrain"},"details":{"precipitation_amount":0.2}},"next_6_hours":{"summary":{"symbol_code":"rain"},"details":{"precipitation_amount":3.1}}}},{"time":"2021-09-24T04:00:00Z","data":{"instant":{"details":{"air_pressure_at_sea_level":1016.3,"air_temperature":15.8,"cloud_area_fraction":100.0,"relative_humidity":97.6,"wind_from_direction":246.0,"wind_speed":6.4}},"next_12_hours":{"summary":{"symbol_code":"rain"}},"next_1_hours":{"summary":{"symbol_code":"lightrain"},"details":{"precipitation_amount":0.1}},"next_6_hours":{"summary":{"symbol_code":"rain"},"details":{"precipitation_amount":3.5}}}},{"time":"2021-09-24T05:00:00Z","data":{"instant":{"details":{"air_pressure_at_sea_level":1015.9,"air_temperature":15.8,"cloud_area_fraction":100.0,"relative_humidity":97.6,"wind_from_direction":244.1,"wind_speed":6.4}},"next_12_hours":{"summary":{"symbol_code":"lightrain"}},"next_1_hours":{"summary":{"symbol_code":"lightrain"},"details":{"precipitation_amount":0.1}},"next_6_hours":{"summary":{"symbol_code":"rain"},"details":{"precipitation_amount":3.6}}}},{"time":"2021-09-24T06:00:00Z","data":{"instant":{"details":{"air_pressure_at_sea_level":1015.8,"air_temperature":15.8,"cloud_area_fraction":100.0,"relative_humidity":97.4,"wind_from_direction":244.9,"wind_speed":6.5}},"next_12_hours":{"summary":{"symbol_code":"lightrain"}},"next_1_hours":{"summary":{"symbol_code":"rain"},"details":{"precipitation_amount":0.6}},"next_6_hours":{"summary":{"symbol_code":"rain"},"details":{"precipitation_amount":3.8}}}},{"time":"2021-09-24T07:00:00Z","data":{"instant":{"details":{"air_pressure_at_sea_level":1015.8,"air_temperature":15.8,"cloud_area_fraction":100.0,"relative_humidity":97.6,"wind_from_direction":246.3,"wind_speed":6.8}},"next_12_hours":{"summary":{"symbol_code":"lightrain"}},"next_1_hours":{"summary":{"symbol_code":"heavyrain"},"details":{"precipitation_amount":1.2}},"next_6_hours":{"summary":{"symbol_code":"rain"},"details":{"precipitation_amount":3.4}}}},{"time":"2021-09-24T08:00:00Z","data":{"instant":{"details":{"air_pressure_at_sea_level":1015.6,"air_temperature":15.9,"cloud_area_fraction":100.0,"relative_humidity":97.2,"wind_from_direction":250.0,"wind_speed":6.8}},"next_12_hours":{"summary":{"symbol_code":"lightrain"}},"next_1_hours":{"summary":{"symbol_code":"rain"},"details":{"precipitation_amount":0.9}},"next_6_hours":{"summary":{"symbol_code":"rain"},"details":{"precipitation_amount":2.3}}}},{"time":"2021-09-24T09:00:00Z","data":{"instant":{"details":{"air_pressure_at_sea_level":1015.8,"air_temperature":16.0,"cloud_area_fraction":100.0,"relative_humidity":96.3,"wind_from_direction":253.4,"wind_speed":6.7}},"next_12_hours":{"summary":{"symbol_code":"lightrain"}},"next_1_hours":{"summary":{"symbol_code":"rain"},"details":{"precipitation_amount":0.6}},"next_6_hours":{"summary":{"symbol_code":"rain"},"details":{"precipitation_amount":1.5}}}},{"time":"2021-09-24T10:00:00Z","data":{"instant":{"details":{"air_pressure_at_sea_level":1016.0,"air_temperature":16.0,"cloud_area_fraction":100.0,"relative_humidity":96.6,"wind_from_direction":255.9,"wind_speed":6.9}},"next_12_hours":{"summary":{"symbol_code":"lightrain"}},"next_1_hours":{"summary":{"symbol_code":"rain"},"details":{"precipitation_amount":0.3}},"next_6_hours":{"summary":{"symbol_code":"rain"},"details":{"precipitation_amount":1.0}}}},{"time":"2021-09-24T11:00:00Z","data":{"instant":{"details":{"air_pressure_at_sea_level":1016.1,"air_temperature":16.1,"cloud_area_fraction":100.0,"relative_humidity":96.1,"wind_from_direction":258.3,"wind_speed":7.1}},"next_12_hours":{"summary":{"symbol_code":"lightrain"}},"next_1_hours":{"summary":{"symbol_code":"rain"},"details":{"precipitation_amount":0.3}},"next_6_hours":{"summary":{"symbol_code":"lightrain"},"details":{"precipitation_amount":0.7}}}},{"time":"2021-09-24T12:00:00Z","data":{"instant":{"details":{"air_pressure_at_sea_level":1016.1,"air_temperature":16.3,"cloud_area_fraction":100.0,"relative_humidity":94.5,"wind_from_direction":262.3,"wind_speed":7.1}},"next_12_hours":{"summary":{"symbol_code":"cloudy"}},"next_1_hours":{"summary":{"symbol_code":"lightrain"},"details":{"precipitation_amount":0.2}},"next_6_hours":{"summary":{"symbol_code":"cloudy"},"details":{"precipitation_amount":0.5}}}},{"time":"2021-09-24T13:00:00Z","data":{"instant":{"details":{"air_pressure_at_sea_level":1016.1,"air_temperature":16.3,"cloud_area_fraction":100.0,"relative_humidity":94.5,"wind_from_direction":266.2,"wind_speed":6.9}},"next_12_hours":{"summary":{"symbol_code":"cloudy"}},"next_1_hours":{"summary":{"symbol_code":"lightrain"},"details":{"precipitation_amount":0.1}},"next_6_hours":{"summary":{"symbol_code":"cloudy"},"details":{"precipitation_amount":0.4}}}},{"time":"2021-09-24T14:00:00Z","data":{"instant":{"details":{"air_pressure_at_sea_level":1015.9,"air_temperature":16.3,"cloud_area_fraction":100.0,"relative_humidity":93.7,"wind_from_direction":263.1,"wind_speed":6.3}},"next_12_hours":{"summary":{"symbol_code":"lightrain"}},"next_1_hours":{"summary":{"symbol_code":"cloudy"},"details":{"precipitation_amount":0.1}},"next_6_hours":{"summary":{"symbol_code":"cloudy"},"details":{"precipitation_amount":0.3}}}},{"time":"2021-09-24T15:00:00Z","data":{"instant":{"details":{"air_pressure_at_sea_level":1015.6,"air_temperature":16.3,"cloud_area_fraction":100.0,"relative_humidity":93.7,"wind_from_direction":258.2,"wind_speed":6.0}},"next_12_hours":{"summary":{"symbol_code":"lightrain"}},"next_1_hours":{"summary":{"symbol_code":"cloudy"},"details":{"precipitation_amount":0.0}},"next_6_hours":{"summary":{"symbol_code":"cloudy"},"details":{"precipitation_amount":0.2}}}},{"time":"2021-09-24T16:00:00Z","data":{"instant":{"details":{"air_pressure_at_sea_level":1015.4,"air_temperature":16.2,"cloud_area_fraction":100.0,"relative_humidity":94.7,"wind_from_direction":257.3,"wind_speed":5.9}},"next_12_hours":{"summary":{"symbol_code":"lightrain"}},"next_1_hours":{"summary":{"symbol_code":"cloudy"},"details":{"precipitation_amount":0.0}},"next_6_hours":{"summary":{"symbol_code":"cloudy"},"details":{"precipitation_amount":0.3}}}},{"time":"2021-09-24T17:00:00Z","data":{"instant":{"details":{"air_pressure_at_sea_level":1015.4,"air_temperature":16.1,"cloud_area_fraction":100.0,"relative_humidity":95.3,"wind_from_direction":257.9,"wind_speed":5.3}},"next_12_hours":{"summary":{"symbol_code":"lightrain"}},"next_1_hours":{"summary":{"symbol_code":"cloudy"},"details":{"precipitation_amount":0.0}},"next_6_hours":{"summary":{"symbol_code":"cloudy"},"details":{"precipitation_amount":0.4}}}},{"time":"2021-09-24T18:00:00Z","data":{"instant":{"details":{"air_pressure_at_sea_level":1015.3,"air_temperature":16.0,"cloud_area_fraction":100.0,"relative_humidity":95.5,"wind_from_direction":256.9,"wind_speed":4.6}},"next_12_hours":{"summary":{"symbol_code":"lightrain"}},"next_1_hours":{"summary":{"symbol_code":"cloudy"},"details":{"precipitation_amount":0.1}},"next_6_hours":{"summary":{"symbol_code":"cloudy"},"details":{"precipitation_amount":0.4}}}},{"time":"2021-09-24T19:00:00Z","data":{"instant":{"details":{"air_pressure_at_sea_level":1015.3,"air_temperature":15.8,"cloud_area_fraction":100.0,"relative_humidity":96.3,"wind_from_direction":257.5,"wind_speed":4.1}},"next_12_hours":{"summary":{"symbol_code":"lightrain"}},"next_1_hours":{"summary":{"symbol_code":"cloudy"},"details":{"precipitation_amount":0.0}},"next_6_hours":{"summary":{"symbol_code":"cloudy"},"details":{"precipitation_amount":0.5}}}},{"time":"2021-09-24T20:00:00Z","data":{"instant":{"details":{"air_pressure_at_sea_level":1015.4,"air_temperature":15.7,"cloud_area_fraction":100.0,"relative_humidity":96.9,"wind_from_direction":251.6,"wind_speed":3.7}},"next_12_hours":{"summary":{"symbol_code":"lightrain"}},"next_1_hours":{"summary":{"symbol_code":"cloudy"},"details":{"precipitation_amount":0.0}},"next_6_hours":{"summary":{"symbol_code":"lightrain"},"details":{"precipitation_amount":0.6}}}},{"time":"2021-09-24T21:00:00Z","data":{"instant":{"details":{"air_pressure_at_sea_level":1015.4,"air_temperature":15.7,"cloud_area_fraction":100.0,"relative_humidity":97.6,"wind_from_direction":238.2,"wind_speed":3.7}},"next_12_hours":{"summary":{"symbol_code":"lightrain"}},"next_1_hours":{"summary":{"symbol_code":"cloudy"},"details":{"precipitation_amount":0.1}},"next_6_hours":{"summary":{"symbol_code":"lightrain"},"details":{"precipitation_amount":0.6}}}},{"time":"2021-09-24T22:00:00Z","data":{"instant":{"details":{"air_pressure_at_sea_level":1015.5,"air_temperature":15.6,"cloud_area_fraction":100.0,"relative_humidity":97.6,"wind_from_direction":230.8,"wind_speed":4.1}},"next_12_hours":{"summary":{"symbol_code":"lightrain"}},"next_1_hours":{"summary":{"symbol_code":"lightrain"},"details":{"precipitation_amount":0.1}},"next_6_hours":{"summary":{"symbol_code":"lightrain"},"details":{"precipitation_amount":0.6}}}},{"time":"2021-09-24T23:00:00Z","data":{"instant":{"details":{"air_pressure_at_sea_level":1015.3,"air_temperature":15.6,"cloud_area_fraction":100.0,"relative_humidity":97.6,"wind_from_direction":230.1,"wind_speed":4.0}},"next_12_hours":{"summary":{"symbol_code":"lightrain"}},"next_1_hours":{"summary":{"symbol_code":"lightrain"},"details":{"precipitation_amount":0.1}},"next_6_hours":{"summary":{"symbol_code":"lightrain"},"details":{"precipitation_amount":0.5}}}},{"time":"2021-09-25T00:00:00Z","data":{"instant":{"details":{"air_pressure_at_sea_level":1014.8,"air_temperature":15.6,"cloud_area_fraction":100.0,"relative_humidity":97.8,"wind_from_direction":228.8,"wind_speed":3.8}},"next_12_hours":{"summary":{"symbol_code":"lightrain"}},"next_1_hours":{"summary":{"symbol_code":"cloudy"},"details":{"precipitation_amount":0.1}},"next_6_hours":{"summary":{"symbol_code":"lightrain"},"details":{"precipitation_amount":0.5}}}},{"time":"2021-09-25T01:00:00Z","data":{"instant":{"details":{"air_pressure_at_sea_level":1014.4,"air_temperature":15.6,"cloud_area_fraction":100.0,"relative_humidity":97.6,"wind_from_direction":226.0,"wind_speed":3.9}},"next_12_hours":{"summary":{"symbol_code":"lightrain"}},"next_1_hours":{"summary":{"symbol_code":"lightrain"},"details":{"precipitation_amount":0.2}},"next_6_hours":{"summary":{"symbol_code":"lightrain"},"details":{"precipitation_amount":0.6}}}},{"time":"2021-09-25T02:00:00Z","data":{"instant":{"details":{"air_pressure_at_sea_level":1013.9,"air_temperature":15.5,"cloud_area_fraction":100.0,"relative_humidity":97.5,"wind_from_direction":226.2,"wind_speed":4.1}},"next_12_hours":{"summary":{"symbol_code":"lightrain"}},"next_1_hours":{"summary":{"symbol_code":"cloudy"},"details":{"precipitation_amount":0.1}},"next_6_hours":{"summary":{"symbol_code":"lightrain"},"details":{"precipitation_amount":0.6}}}},{"time":"2021-09-25T03:00:00Z","data":{"instant":{"details":{"air_pressure_at_sea_level":1013.4,"air_temperature":15.4,"cloud_area_fraction":100.0,"relative_humidity":97.5,"wind_from_direction":224.0,"wind_speed":4.0}},"next_12_hours":{"summary":{"symbol_code":"lightrain"}},"next_1_hours":{"summary":{"symbol_code":"cloudy"},"details":{"precipitation_amount":0.1}},"next_6_hours":{"summary":{"symbol_code":"lightrain"},"details":{"precipitation_amount":0.6}}}},{"time":"2021-09-25T04:00:00Z","data":{"instant":{"details":{"air_pressure_at_sea_level":1013.0,"air_temperature":15.3,"cloud_area_fraction":94.5,"relative_humidity":97.6,"wind_from_direction":222.7,"wind_speed":3.8}},"next_12_hours":{"summary":{"symbol_code":"lightrain"}},"next_1_hours":{"summary":{"symbol_code":"cloudy"},"details":{"precipitation_amount":0.0}},"next_6_hours":{"summary":{"symbol_code":"lightrain"},"details":{"precipitation_amount":0.6}}}},{"time":"2021-09-25T05:00:00Z","data":{"instant":{"details":{"air_pressure_at_sea_level":1012.6,"air_temperature":15.2,"cloud_area_fraction":96.9,"relative_humidity":97.6,"wind_from_direction":221.1,"wind_speed":3.9}},"next_12_hours":{"summary":{"symbol_code":"lightrain"}},"next_1_hours":{"summary":{"symbol_code":"lightrain"},"details":{"precipitation_amount":0.1}},"next_6_hours":{"summary":{"symbol_code":"lightrain"},"details":{"precipitation_amount":0.6}}}},{"time":"2021-09-25T06:00:00Z","data":{"instant":{"details":{"air_pressure_at_sea_level":1012.3,"air_temperature":15.1,"cloud_area_fraction":100.0,"relative_humidity":97.9,"wind_from_direction":220.0,"wind_speed":3.8}},"next_12_hours":{"summary":{"symbol_code":"lightrain"}},"next_1_hours":{"summary":{"symbol_code":"lightrain"},"details":{"precipitation_amount":0.2}},"next_6_hours":{"summary":{"symbol_code":"lightrain"},"details":{"precipitation_amount":0.5}}}},{"time":"2021-09-25T07:00:00Z","data":{"instant":{"details":{"air_pressure_at_sea_level":1012.2,"air_temperature":15.3,"cloud_area_fraction":100.0,"relative_humidity":96.5,"wind_from_direction":219.7,"wind_speed":4.1}},"next_12_hours":{"summary":{"symbol_code":"cloudy"}},"next_1_hours":{"summary":{"symbol_code":"lightrain"},"details":{"precipitation_amount":0.2}},"next_6_hours":{"summary":{"symbol_code":"cloudy"},"details":{"precipitation_amount":0.4}}}},{"time":"2021-09-25T08:00:00Z","data":{"instant":{"details":{"air_pressure_at_sea_level":1012.2,"air_temperature":15.4,"cloud_area_fraction":94.5,"relative_humidity":95.6,"wind_from_direction":222.7,"wind_speed":4.5}},"next_12_hours":{"summary":{"symbol_code":"cloudy"}},"next_1_hours":{"summary":{"symbol_code":"partlycloudy_day"},"details":{"precipitation_amount":0.1}},"next_6_hours":{"summary":{"symbol_code":"cloudy"},"details":{"precipitation_amount":0.2}}}},{"time":"2021-09-25T09:00:00Z","data":{"instant":{"details":{"air_pressure_at_sea_level":1012.2,"air_temperature":15.6,"cloud_area_fraction":79.7,"relative_humidity":93.8,"wind_from_direction":218.5,"wind_speed":4.6}},"next_12_hours":{"summary":{"symbol_code":"cloudy"}},"next_1_hours":{"summary":{"symbol_code":"partlycloudy_day"},"details":{"precipitation_amount":0.0}},"next_6_hours":{"summary":{"symbol_code":"cloudy"},"details":{"precipitation_amount":0.1}}}},{"time":"2021-09-25T10:00:00Z","data":{"instant":{"details":{"air_pressure_at_sea_level":1012.0,"air_temperature":16.0,"cloud_area_fraction":81.2,"relative_humidity":88.1,"wind_from_direction":217.5,"wind_speed":5.1}},"next_12_hours":{"summary":{"symbol_code":"cloudy"}},"next_1_hours":{"summary":{"symbol_code":"partlycloudy_day"},"details":{"precipitation_amount":0.0}},"next_6_hours":{"summary":{"symbol_code":"cloudy"},"details":{"precipitation_amount":0.1}}}},{"time":"2021-09-25T11:00:00Z","data":{"instant":{"details":{"air_pressure_at_sea_level":1011.8,"air_temperature":16.3,"cloud_area_fraction":85.2,"relative_humidity":85.0,"wind_from_direction":211.6,"wind_speed":5.1}},"next_12_hours":{"summary":{"symbol_code":"cloudy"}},"next_1_hours":{"summary":{"symbol_code":"cloudy"},"details":{"precipitation_amount":0.0}},"next_6_hours":{"summary":{"symbol_code":"cloudy"},"details":{"precipitation_amount":0.1}}}},{"time":"2021-09-25T12:00:00Z","data":{"instant":{"details":{"air_pressure_at_sea_level":1011.4,"air_temperature":16.7,"cloud_area_fraction":94.5,"relative_humidity":81.3,"wind_from_direction":210.8,"wind_speed":4.9}},"next_12_hours":{"summary":{"symbol_code":"cloudy"}},"next_1_hours":{"summary":{"symbol_code":"cloudy"},"details":{"precipitation_amount":0.0}},"next_6_hours":{"summary":{"symbol_code":"cloudy"},"details":{"precipitation_amount":0.1}}}},{"time":"2021-09-25T13:00:00Z","data":{"instant":{"details":{"air_pressure_at_sea_level":1010.7,"air_temperature":17.2,"cloud_area_fraction":96.9,"relative_humidity":78.0,"wind_from_direction":213.5,"wind_speed":4.9}},"next_12_hours":{"summary":{"symbol_code":"cloudy"}},"next_1_hours":{"summary":{"symbol_code":"cloudy"},"details":{"precipitation_amount":0.0}},"next_6_hours":{"summary":{"symbol_code":"cloudy"},"details":{"precipitation_amount":0.1}}}},{"time":"2021-09-25T14:00:00Z","data":{"instant":{"details":{"air_pressure_at_sea_level":1010.2,"air_temperature":17.4,"cloud_area_fraction":89.1,"relative_humidity":78.3,"wind_from_direction":223.4,"wind_speed":4.8}},"next_12_hours":{"summary":{"symbol_code":"cloudy"}},"next_1_hours":{"summary":{"symbol_code":"cloudy"},"details":{"precipitation_amount":0.0}},"next_6_hours":{"summary":{"symbol_code":"cloudy"},"details":{"precipitation_amount":0.1}}}},{"time":"2021-09-25T15:00:00Z","data":{"instant":{"details":{"air_pressure_at_sea_level":1009.8,"air_temperature":17.1,"cloud_area_fraction":96.9,"relative_humidity":80.5,"wind_from_direction":236.8,"wind_speed":4.1}},"next_12_hours":{"summary":{"symbol_code":"cloudy"}},"next_1_hours":{"summary":{"symbol_code":"cloudy"},"details":{"precipitation_amount":0.0}},"next_6_hours":{"summary":{"symbol_code":"cloudy"},"details":{"precipitation_amount":0.1}}}},{"time":"2021-09-25T16:00:00Z","data":{"instant":{"details":{"air_pressure_at_sea_level":1009.5,"air_temperature":16.8,"cloud_area_fraction":100.0,"relative_humidity":82.4,"wind_from_direction":236.1,"wind_speed":3.5}},"next_12_hours":{"summary":{"symbol_code":"cloudy"}},"next_1_hours":{"summary":{"symbol_code":"cloudy"},"details":{"precipitation_amount":0.0}},"next_6_hours":{"summary":{"symbol_code":"cloudy"},"details":{"precipitation_amount":0.1}}}},{"time":"2021-09-25T17:00:00Z","data":{"instant":{"details":{"air_pressure_at_sea_level":1009.0,"air_temperature":16.4,"cloud_area_fraction":100.0,"relative_humidity":85.3,"wind_from_direction":229.7,"wind_speed":3.8}},"next_12_hours":{"summary":{"symbol_code":"cloudy"}},"next_1_hours":{"summary":{"symbol_code":"cloudy"},"details":{"precipitation_amount":0.0}},"next_6_hours":{"summary":{"symbol_code":"cloudy"},"details":{"precipitation_amount":0.0}}}},{"time":"2021-09-25T18:00:00Z","data":{"instant":{"details":{"air_pressure_at_sea_level":1008.4,"air_temperature":16.1,"cloud_area_fraction":97.7,"relative_humidity":87.3,"wind_from_direction":214.1,"wind_speed":3.8}},"next_12_hours":{"summary":{"symbol_code":"cloudy"}},"next_1_hours":{"summary":{"symbol_code":"cloudy"},"details":{"precipitation_amount":0.0}},"next_6_hours":{"summary":{"symbol_code":"cloudy"},"details":{"precipitation_amount":0.0}}}},{"time":"2021-09-25T19:00:00Z","data":{"instant":{"details":{"air_pressure_at_sea_level":1007.9,"air_temperature":16.1,"cloud_area_fraction":99.2,"relative_humidity":87.7,"wind_from_direction":194.8,"wind_speed":3.5}},"next_1_hours":{"summary":{"symbol_code":"cloudy"},"details":{"precipitation_amount":0.0}},"next_6_hours":{"summary":{"symbol_code":"cloudy"},"details":{"precipitation_amount":0.0}}}},{"time":"2021-09-25T20:00:00Z","data":{"instant":{"details":{"air_pressure_at_sea_level":1007.5,"air_temperature":16.3,"cloud_area_fraction":100.0,"relative_humidity":86.7,"wind_from_direction":174.2,"wind_speed":3.9}},"next_1_hours":{"summary":{"symbol_code":"cloudy"},"details":{"precipitation_amount":0.0}},"next_6_hours":{"summary":{"symbol_code":"cloudy"},"details":{"precipitation_amount":0.0}}}},{"time":"2021-09-25T21:00:00Z","data":{"instant":{"details":{"air_pressure_at_sea_level":1007.2,"air_temperature":16.5,"cloud_area_fraction":99.2,"relative_humidity":84.4,"wind_from_direction":176.6,"wind_speed":4.7}},"next_1_hours":{"summary":{"symbol_code":"cloudy"},"details":{"precipitation_amount":0.0}},"next_6_hours":{"summary":{"symbol_code":"cloudy"},"details":{"precipitation_amount":0.0}}}},{"time":"2021-09-25T22:00:00Z","data":{"instant":{"details":{"air_pressure_at_sea_level":1006.8,"air_temperature":16.3,"cloud_area_fraction":99.2,"relative_humidity":85.7,"wind_from_direction":174.0,"wind_speed":4.8}},"next_1_hours":{"summary":{"symbol_code":"cloudy"},"details":{"precipitation_amount":0.0}},"next_6_hours":{"summary":{"symbol_code":"partlycloudy_night"},"details":{"precipitation_amount":0.0}}}},{"time":"2021-09-25T23:00:00Z","data":{"instant":{"details":{"air_pressure_at_sea_level":1006.2,"air_temperature":16.0,"cloud_area_fraction":99.2,"relative_humidity":86.7,"wind_from_direction":168.9,"wind_speed":5.2}},"next_1_hours":{"summary":{"symbol_code":"cloudy"},"details":{"precipitation_amount":0.0}},"next_6_hours":{"summary":{"symbol_code":"partlycloudy_night"},"details":{"precipitation_amount":0.0}}}},{"time":"2021-09-26T00:00:00Z","data":{"instant":{"details":{"air_pressure_at_sea_level":1005.6,"air_temperature":15.9,"cloud_area_fraction":100.0,"relative_humidity":87.7,"wind_from_direction":167.7,"wind_speed":5.5}},"next_12_hours":{"summary":{"symbol_code":"lightrain"}},"next_1_hours":{"summary":{"symbol_code":"cloudy"},"details":{"precipitation_amount":0.0}},"next_6_hours":{"summary":{"symbol_code":"partlycloudy_night"},"details":{"precipitation_amount":0.0}}}},{"time":"2021-09-26T01:00:00Z","data":{"instant":{"details":{"air_pressure_at_sea_level":1004.9,"air_temperature":15.9,"cloud_area_fraction":88.3,"relative_humidity":87.9,"wind_from_direction":168.2,"wind_speed":5.5}},"next_1_hours":{"summary":{"symbol_code":"partlycloudy_night"},"details":{"precipitation_amount":0.0}}}},{"time":"2021-09-26T02:00:00Z","data":{"instant":{"details":{"air_pressure_at_sea_level":1004.1,"air_temperature":15.7,"cloud_area_fraction":58.6,"relative_humidity":88.4,"wind_from_direction":166.5,"wind_speed":5.6}},"next_1_hours":{"summary":{"symbol_code":"partlycloudy_night"},"details":{"precipitation_amount":0.0}}}},{"time":"2021-09-26T03:00:00Z","data":{"instant":{"details":{"air_pressure_at_sea_level":1003.2,"air_temperature":15.4,"cloud_area_fraction":82.8,"relative_humidity":90.4,"wind_from_direction":160.4,"wind_speed":5.9}},"next_1_hours":{"summary":{"symbol_code":"partlycloudy_night"},"details":{"precipitation_amount":0.0}}}},{"time":"2021-09-26T04:00:00Z","data":{"instant":{"details":{"air_pressure_at_sea_level":1002.3,"air_temperature":15.6,"cloud_area_fraction":73.4,"relative_humidity":89.6,"wind_from_direction":158.6,"wind_speed":6.3}},"next_1_hours":{"summary":{"symbol_code":"cloudy"},"details":{"precipitation_amount":0.0}}}},{"time":"2021-09-26T05:00:00Z","data":{"instant":{"details":{"air_pressure_at_sea_level":1001.8,"air_temperature":15.8,"cloud_area_fraction":97.7,"relative_humidity":88.4,"wind_from_direction":165.6,"wind_speed":6.6}},"next_1_hours":{"summary":{"symbol_code":"fair_night"},"details":{"precipitation_amount":0.0}}}},{"time":"2021-09-26T06:00:00Z","data":{"instant":{"details":{"air_pressure_at_sea_level":1001.3,"air_temperature":15.9,"cloud_area_fraction":92.2,"relative_humidity":88.2,"wind_from_direction":165.9,"wind_speed":6.7}},"next_12_hours":{"summary":{"symbol_code":"rain"}},"next_6_hours":{"summary":{"symbol_code":"rain"},"details":{"precipitation_amount":2.8}}}},{"time":"2021-09-26T12:00:00Z","data":{"instant":{"details":{"air_pressure_at_sea_level":998.9,"air_temperature":14.5,"cloud_area_fraction":100.0,"relative_humidity":89.8,"wind_from_direction":269.4,"wind_speed":7.1}},"next_12_hours":{"summary":{"symbol_code":"lightrainshowers_day"}},"next_6_hours":{"summary":{"symbol_code":"heavyrain"},"details":{"precipitation_amount":6.0}}}},{"time":"2021-09-26T18:00:00Z","data":{"instant":{"details":{"air_pressure_at_sea_level":1000.5,"air_temperature":12.3,"cloud_area_fraction":100.0,"relative_humidity":78.6,"wind_from_direction":260.1,"wind_speed":4.1}},"next_12_hours":{"summary":{"symbol_code":"partlycloudy_night"}},"next_6_hours":{"summary":{"symbol_code":"rainshowers_night"},"details":{"precipitation_amount":1.9}}}},{"time":"2021-09-27T00:00:00Z","data":{"instant":{"details":{"air_pressure_at_sea_level":1001.4,"air_temperature":10.9,"cloud_area_fraction":52.3,"relative_humidity":87.7,"wind_from_direction":225.4,"wind_speed":6.2}},"next_12_hours":{"summary":{"symbol_code":"rainshowers_day"}},"next_6_hours":{"summary":{"symbol_code":"heavyrainshowers_night"},"details":{"precipitation_amount":9.0}}}},{"time":"2021-09-27T06:00:00Z","data":{"instant":{"details":{"air_pressure_at_sea_level":1002.8,"air_temperature":10.5,"cloud_area_fraction":85.9,"relative_humidity":86.4,"wind_from_direction":214.0,"wind_speed":7.2}},"next_12_hours":{"summary":{"symbol_code":"heavyrainshowers_day"}},"next_6_hours":{"summary":{"symbol_code":"heavyrainshowers_day"},"details":{"precipitation_amount":13.2}}}},{"time":"2021-09-27T12:00:00Z","data":{"instant":{"details":{"air_pressure_at_sea_level":1006.3,"air_temperature":12.3,"cloud_area_fraction":80.5,"relative_humidity":77.3,"wind_from_direction":235.8,"wind_speed":9.3}},"next_12_hours":{"summary":{"symbol_code":"lightrainshowers_day"}},"next_6_hours":{"summary":{"symbol_code":"heavyrainshowers_day"},"details":{"precipitation_amount":8.0}}}},{"time":"2021-09-27T18:00:00Z","data":{"instant":{"details":{"air_pressure_at_sea_level":1009.7,"air_temperature":11.4,"cloud_area_fraction":82.8,"relative_humidity":79.1,"wind_from_direction":252.0,"wind_speed":9.4}},"next_12_hours":{"summary":{"symbol_code":"rain"}},"next_6_hours":{"summary":{"symbol_code":"heavyrainshowers_night"},"details":{"precipitation_amount":10.9}}}},{"time":"2021-09-28T00:00:00Z","data":{"instant":{"details":{"air_pressure_at_sea_level":1013.5,"air_temperature":11.2,"cloud_area_fraction":78.9,"relative_humidity":82.3,"wind_from_direction":245.1,"wind_speed":6.4}},"next_12_hours":{"summary":{"symbol_code":"rain"}},"next_6_hours":{"summary":{"symbol_code":"heavyrain"},"details":{"precipitation_amount":5.6}}}},{"time":"2021-09-28T06:00:00Z","data":{"instant":{"details":{"air_pressure_at_sea_level":1015.0,"air_temperature":10.4,"cloud_area_fraction":99.2,"relative_humidity":87.0,"wind_from_direction":228.7,"wind_speed":5.6}},"next_12_hours":{"summary":{"symbol_code":"lightrainshowers_day"}},"next_6_hours":{"summary":{"symbol_code":"rain"},"details":{"precipitation_amount":2.1}}}},{"time":"2021-09-28T12:00:00Z","data":{"instant":{"details":{"air_pressure_at_sea_level":1015.5,"air_temperature":11.4,"cloud_area_fraction":96.1,"relative_humidity":77.1,"wind_from_direction":191.8,"wind_speed":2.4}},"next_12_hours":{"summary":{"symbol_code":"partlycloudy_day"}},"next_6_hours":{"summary":{"symbol_code":"partlycloudy_day"},"details":{"precipitation_amount":0.3}}}},{"time":"2021-09-28T18:00:00Z","data":{"instant":{"details":{"air_pressure_at_sea_level":1016.5,"air_temperature":11.3,"cloud_area_fraction":30.5,"relative_humidity":85.4,"wind_from_direction":267.5,"wind_speed":3.6}},"next_12_hours":{"summary":{"symbol_code":"partlycloudy_night"}},"next_6_hours":{"summary":{"symbol_code":"partlycloudy_night"},"details":{"precipitation_amount":0.3}}}},{"time":"2021-09-29T00:00:00Z","data":{"instant":{"details":{"air_pressure_at_sea_level":1017.6,"air_temperature":11.7,"cloud_area_fraction":57.8,"relative_humidity":78.3,"wind_from_direction":216.7,"wind_speed":4.2}},"next_12_hours":{"summary":{"symbol_code":"lightrainshowers_day"}},"next_6_hours":{"summary":{"symbol_code":"rainshowers_night"},"details":{"precipitation_amount":1.1}}}},{"time":"2021-09-29T06:00:00Z","data":{"instant":{"details":{"air_pressure_at_sea_level":1015.3,"air_temperature":11.1,"cloud_area_fraction":59.4,"relative_humidity":88.7,"wind_from_direction":172.8,"wind_speed":4.5}},"next_12_hours":{"summary":{"symbol_code":"rain"}},"next_6_hours":{"summary":{"symbol_code":"lightrainshowers_day"},"details":{"precipitation_amount":0.6}}}},{"time":"2021-09-29T12:00:00Z","data":{"instant":{"details":{"air_pressure_at_sea_level":1017.1,"air_temperature":14.1,"cloud_area_fraction":96.1,"relative_humidity":78.4,"wind_from_direction":265.5,"wind_speed":7.5}},"next_12_hours":{"summary":{"symbol_code":"rain"}},"next_6_hours":{"summary":{"symbol_code":"heavyrain"},"details":{"precipitation_amount":7.2}}}},{"time":"2021-09-29T18:00:00Z","data":{"instant":{"details":{"air_pressure_at_sea_level":1013.3,"air_temperature":14.5,"cloud_area_fraction":100.0,"relative_humidity":96.2,"wind_from_direction":233.3,"wind_speed":8.2}},"next_12_hours":{"summary":{"symbol_code":"lightrain"}},"next_6_hours":{"summary":{"symbol_code":"rain"},"details":{"precipitation_amount":3.3}}}},{"time":"2021-09-30T00:00:00Z","data":{"instant":{"details":{"air_pressure_at_sea_level":1014.4,"air_temperature":11.9,"cloud_area_fraction":99.2,"relative_humidity":92.6,"wind_from_direction":2.5,"wind_speed":3.2}},"next_12_hours":{"summary":{"symbol_code":"cloudy"}},"next_6_hours":{"summary":{"symbol_code":"cloudy"},"details":{"precipitation_amount":0.0}}}},{"time":"2021-09-30T06:00:00Z","data":{"instant":{"details":{"air_pressure_at_sea_level":1016.3,"air_temperature":10.7,"cloud_area_fraction":93.7,"relative_humidity":87.5,"wind_from_direction":342.6,"wind_speed":3.0}},"next_12_hours":{"summary":{"symbol_code":"cloudy"}},"next_6_hours":{"summary":{"symbol_code":"cloudy"},"details":{"precipitation_amount":0.0}}}},{"time":"2021-09-30T12:00:00Z","data":{"instant":{"details":{"air_pressure_at_sea_level":1018.9,"air_temperature":13.5,"cloud_area_fraction":100.0,"relative_humidity":63.9,"wind_from_direction":306.0,"wind_speed":3.9}},"next_12_hours":{"summary":{"symbol_code":"cloudy"}},"next_6_hours":{"summary":{"symbol_code":"cloudy"},"details":{"precipitation_amount":0.0}}}},{"time":"2021-09-30T18:00:00Z","data":{"instant":{"details":{"air_pressure_at_sea_level":1019.5,"air_temperature":12.5,"cloud_area_fraction":74.2,"relative_humidity":65.4,"wind_from_direction":296.4,"wind_speed":3.6}},"next_12_hours":{"summary":{"symbol_code":"cloudy"}},"next_6_hours":{"summary":{"symbol_code":"cloudy"},"details":{"precipitation_amount":0.0}}}},{"time":"2021-10-01T00:00:00Z","data":{"instant":{"details":{"air_pressure_at_sea_level":1018.2,"air_temperature":11.3,"cloud_area_fraction":99.2,"relative_humidity":79.7,"wind_from_direction":181.0,"wind_speed":4.3}},"next_12_hours":{"summary":{"symbol_code":"rain"}},"next_6_hours":{"summary":{"symbol_code":"cloudy"},"details":{"precipitation_amount":0.0}}}},{"time":"2021-10-01T06:00:00Z","data":{"instant":{"details":{"air_pressure_at_sea_level":1011.3,"air_temperature":11.6,"cloud_area_fraction":100.0,"relative_humidity":75.8,"wind_from_direction":172.4,"wind_speed":7.1}},"next_12_hours":{"summary":{"symbol_code":"heavyrain"}},"next_6_hours":{"summary":{"symbol_code":"heavyrain"},"details":{"precipitation_amount":5.1}}}},{"time":"2021-10-01T12:00:00Z","data":{"instant":{"details":{"air_pressure_at_sea_level":1002.9,"air_temperature":14.9,"cloud_area_fraction":100.0,"relative_humidity":91.7,"wind_from_direction":198.6,"wind_speed":10.3}},"next_12_hours":{"summary":{"symbol_code":"rain"}},"next_6_hours":{"summary":{"symbol_code":"heavyrain"},"details":{"precipitation_amount":6.5}}}},{"time":"2021-10-01T18:00:00Z","data":{"instant":{"details":{"air_pressure_at_sea_level":999.9,"air_temperature":14.7,"cloud_area_fraction":96.1,"relative_humidity":86.6,"wind_from_direction":231.0,"wind_speed":9.4}},"next_12_hours":{"summary":{"symbol_code":"lightrain"}},"next_6_hours":{"summary":{"symbol_code":"rain"},"details":{"precipitation_amount":1.1}}}},{"time":"2021-10-02T00:00:00Z","data":{"instant":{"details":{"air_pressure_at_sea_level":997.5,"air_temperature":13.6,"cloud_area_fraction":99.2,"relative_humidity":86.7,"wind_from_direction":233.8,"wind_speed":11.4}},"next_12_hours":{"summary":{"symbol_code":"lightrain"}},"next_6_hours":{"summary":{"symbol_code":"cloudy"},"details":{"precipitation_amount":0.5}}}},{"time":"2021-10-02T06:00:00Z","data":{"instant":{"details":{"air_pressure_at_sea_level":995.6,"air_temperature":13.4,"cloud_area_fraction":85.9,"relative_humidity":73.7,"wind_from_direction":240.2,"wind_speed":9.9}},"next_12_hours":{"summary":{"symbol_code":"rainshowers_day"}},"next_6_hours":{"summary":{"symbol_code":"rain"},"details":{"precipitation_amount":4.2}}}},{"time":"2021-10-02T12:00:00Z","data":{"instant":{"details":{"air_pressure_at_sea_level":995.0,"air_temperature":12.9,"cloud_area_fraction":98.4,"relative_humidity":83.1,"wind_from_direction":230.2,"wind_speed":7.8}},"next_6_hours":{"summary":{"symbol_code":"rainshowers_day"},"details":{"precipitation_amount":2.0}}}},{"time":"2021-10-02T18:00:00Z","data":{"instant":{"details":{"air_pressure_at_sea_level":996.4,"air_temperature":12.5,"cloud_area_fraction":33.6,"relative_humidity":72.2,"wind_from_direction":285.7,"wind_speed":9.8}}}}]}}
}